na_quantors/__init__.py
na_quantors/core/__init__.py
na_quantors/tests/__init__.py
na_quantors/tests/test_1984.py
na_quantors-1.0.5.dist-info/LICENSE.txt
na_quantors-1.0.5.dist-info/METADATA
na_quantors-1.0.5.dist-info/WHEEL
na_quantors-1.0.5.dist-info/top_level.txt
na_quantors-1.0.5.dist-info/RECORD
