Metadata-Version: 2.2
Name: na_quantors
Version: 1.0.5
Summary: na_quantors
Author-email: Johannes <johannes-programming@mailfence.com>
License: The MIT License (MIT)
Project-URL: Download, https://pypi.org/project/na-quantors/#files
Project-URL: Index, https://pypi.org/project/na_quantors/
Project-URL: Source, https://github.com/johannes-programming/na_quantors/
Project-URL: Website, https://na-quantors.johannes-programming.online/
Classifier: Development Status :: 5 - Production/Stable
Classifier: License :: OSI Approved :: MIT License
Classifier: Natural Language :: English
Classifier: Operating System :: OS Independent
Classifier: Programming Language :: Python
Classifier: Programming Language :: Python :: 3
Classifier: Programming Language :: Python :: 3 :: Only
Requires-Python: >=3.11
License-File: LICENSE.txt
Requires-Dist: pandas>=2.1.2
